{
  "fetchedAt": "2026-07-19T13:54:23.974189+00:00",
  "gold": {
    "price": 4019.300049,
    "updatedAt": "2026-07-19T13:53:53Z"
  },
  "silver": {
    "price": 56.080002,
    "updatedAt": "2026-07-19T13:53:52Z"
  },
  "dxy": null,
  "vix": {
    "value": 18.77,
    "changePct": 12.19
  },
  "wti": null,
  "btc": {
    "value": 64455.29,
    "changePct": -0.53
  },
  "spx": {
    "value": 7457.69,
    "changePct": -1.01
  },
  "fred": {
    "10y_treasury": {
      "date": "2026-07-16",
      "value": 4.57
    },
    "10y_real_rate": {
      "date": "2026-07-16",
      "value": 2.35
    }
  },
  "goldapi": null,
  "correlations": {
    "dataPoints": 1,
    "minRequired": 10,
    "dxy": null,
    "realRate": null,
    "vix": null,
    "btc": null,
    "spx": null
  },
  "news": [
    {
      "time": "13:53",
      "text": "乌克兰总统弗拉基米尔·泽连斯基任命谢尔盖·科雷茨基（Sergii Koretskyi）为总理，以筹备乌克兰挺过又一个战争寒冬。48岁的科雷茨基既没有内阁经验，也没有政治背景；在近30年的能源界技术官僚职业生涯中，大部分时间都在私营部门工作，"
    },
    {
      "time": "13:44",
      "text": "伊朗Abadan地区传出爆炸声。（伊朗媒体IRIB）"
    },
    {
      "time": "13:38",
      "text": "国际原子能机构19日表示，正在调查有关伊朗达尔霍温在建核电站建设工地夜间遭袭相关事宜。国际原子能机构表示，该核电站目前仍处于建设初期，机构上次到访时现场没有任何核材料。因此，目前认为此次袭击不会造成放射性风险。"
    },
    {
      "time": "13:34",
      "text": "在一届充满大比分胜负的世界杯期间，预测市场交易激增，其增速远超传统体育博彩公司，凸显了Kalshi等公司对体育博彩行业构成的竞争威胁。作为最大的参与者，Kalshi在世界杯期间屡次打破其自身的交易纪录，其交易量不仅翻倍超越了就在锦标赛开始前"
    },
    {
      "time": "13:30",
      "text": "据国际文传电讯社（Interfax）援引俄罗斯国防部的消息报道，俄罗斯无人机袭击了乌克兰最北部哈尔科夫（Kharkiv）地区的一座天然气加工厂。此外，俄罗斯军队还袭击了切尔尼戈夫地区的一个军事物流中心。"
    },
    {
      "time": "13:22",
      "text": "科威特电力、水利和可再生能源部19日发表声明说，该国17日遭袭的发电及海水淡化厂当天再次遭到袭击。这是该国三天内第三次有发电及海水淡化厂遭袭。"
    },
    {
      "time": "13:22",
      "text": "约旦武装部队19日发表声明说，约旦防空系统拦截并击落3枚来自伊朗的导弹，另有1枚导弹落入约旦南部偏远地区。声明说，事件未造成人员伤亡和财产损失。军方已对导弹坠落地点进行安全防护。约旦武装部队将继续保持最高级别的戒备状态，密切监控约旦领空，并"
    },
    {
      "time": "13:21",
      "text": "当地时间18日晚，秘鲁胡宁大区丘帕卡市以南发生5.1级地震。秘鲁国家应急指挥中心通报称，地震已致5人死亡，200人受灾。（央视）"
    },
    {
      "time": "13:19",
      "text": "伊朗：美国近期发动的袭击已造成伊朗超过50人罹难，517人受伤。"
    },
    {
      "time": "13:08",
      "text": "美国能源部长Wright声称：无论伊朗是否提供帮助，（美方）都将确保霍尔木兹海峡的石油输送。\n海峡石油流动的“七天截尾均值”低于700万桶/日，“阿拉伯湾地区”（即波斯湾地区）的石油供应量略微低于1400万桶/日。\n船只继续按照两条线路通过"
    },
    {
      "time": "12:55",
      "text": "Kalshi在世界杯期间新增300万用户。（CNBC）"
    },
    {
      "time": "12:52",
      "text": "约旦军方：拦截了三枚来袭的导弹。\n第四枚导弹命中南部一个空旷区域。（Almamlaka TV）"
    },
    {
      "time": "12:42",
      "text": "随着特斯拉确认了今年德国市场需求将更为强劲的预期，公司正计划扩大新市场，并同步提升其位于德国格伦海德（Gruenheide）工厂的产量。\n“对于2026财年，公司预测其产量将较上一年度实现大幅增长，并预计产能利用率也会相应提高，”特斯拉勃兰"
    },
    {
      "time": "12:37",
      "text": "波音公司：预计737-7飞机将在“近期”获得认证。\n公司接近完成737-10飞机的测试工作。\n将在2027年向客户们交付777X飞机。"
    },
    {
      "time": "12:36",
      "text": "伊朗外交部长阿巴斯·阿拉格齐（Abbas Araghchi）在周日发布于其官方Telegram频道的一段采访中表示：“在核领域存在一些无法解决的问题，也许即使在当前局势下，这些问题依然无法解决。”\n在被问及伊朗在与美国谈判中的红线（包括暂停"
    },
    {
      "time": "07-16 23:00",
      "text": "[Fed] Jefferson, Navigating Economic Shocks: A Monetary Policymaker’s Perspective"
    },
    {
      "time": "07-15 17:00",
      "text": "[Fed] Cook, Economic Outlook"
    },
    {
      "time": "07-14 18:55",
      "text": "[Fed] Bowman, Responsible Innovation and Financial Inclusion"
    },
    {
      "time": "07-14 18:00",
      "text": "[Fed] Minutes of the Board's discount rate meetings on June 8 and June 17, 2026"
    },
    {
      "time": "07-14 16:40",
      "text": "[Fed] Barr, Will Artificial Intelligence Broadly Raise Living Standards or Drive Income and Wealth Inequality?"
    },
    {
      "time": "07-14 12:30",
      "text": "[Fed] Warsh, Semiannual Monetary Policy Report to the Congress"
    }
  ],
  "newsDebug": {
    "fedError": null,
    "wscnError": null,
    "avError": "节流跳过(Alpha Vantage每4小时才调用一次,避免超出免费额度)"
  },
  "priceAction": {
    "alwaysIn": "long",
    "bullTrendBarsInLast3": 0,
    "bearTrendBarsInLast3": 0,
    "isTrendStructure": false,
    "signalBarBull": false,
    "signalBarPrice": 4014.8,
    "measuredMoveLow": 4051.75,
    "measuredMoveHigh": 4084.7,
    "sma20": 4001.02,
    "currentPrice": 4018.8
  },
  "bars1h": [
    {
      "open": 4041.800048828125,
      "high": 4043.10009765625,
      "low": 4037.0,
      "close": 4038.300048828125
    },
    {
      "open": 4038.199951171875,
      "high": 4051.800048828125,
      "low": 4030.300048828125,
      "close": 4032.199951171875
    },
    {
      "open": 4032.39990234375,
      "high": 4041.5,
      "low": 4027.699951171875,
      "close": 4035.800048828125
    },
    {
      "open": 4035.60009765625,
      "high": 4037.10009765625,
      "low": 4027.800048828125,
      "close": 4036.10009765625
    },
    {
      "open": 4035.5,
      "high": 4041.699951171875,
      "low": 4030.0,
      "close": 4040.300048828125
    },
    {
      "open": 4040.60009765625,
      "high": 4043.199951171875,
      "low": 4035.699951171875,
      "close": 4037.39990234375
    },
    {
      "open": 4037.199951171875,
      "high": 4040.10009765625,
      "low": 4034.39990234375,
      "close": 4035.10009765625
    },
    {
      "open": 4035.199951171875,
      "high": 4048.39990234375,
      "low": 4026.199951171875,
      "close": 4044.10009765625
    },
    {
      "open": 4044.39990234375,
      "high": 4048.699951171875,
      "low": 3994.199951171875,
      "close": 3996.39990234375
    },
    {
      "open": 3996.300048828125,
      "high": 4012.60009765625,
      "low": 3977.10009765625,
      "close": 3994.0
    },
    {
      "open": 3993.89990234375,
      "high": 4011.0,
      "low": 3991.199951171875,
      "close": 4002.0
    },
    {
      "open": 4002.199951171875,
      "high": 4021.800048828125,
      "low": 3993.300048828125,
      "close": 4011.800048828125
    },
    {
      "open": 4011.39990234375,
      "high": 4012.300048828125,
      "low": 3986.5,
      "close": 3996.39990234375
    },
    {
      "open": 3996.699951171875,
      "high": 3997.300048828125,
      "low": 3983.89990234375,
      "close": 3989.5
    },
    {
      "open": 3989.699951171875,
      "high": 3995.199951171875,
      "low": 3981.0,
      "close": 3984.699951171875
    },
    {
      "open": 3984.89990234375,
      "high": 3990.800048828125,
      "low": 3973.39990234375,
      "close": 3984.60009765625
    },
    {
      "open": 3984.800048828125,
      "high": 3984.800048828125,
      "low": 3976.199951171875,
      "close": 3979.89990234375
    },
    {
      "open": 3980.10009765625,
      "high": 3984.10009765625,
      "low": 3976.800048828125,
      "close": 3982.10009765625
    },
    {
      "open": 3982.10009765625,
      "high": 3989.89990234375,
      "low": 3978.60009765625,
      "close": 3989.199951171875
    },
    {
      "open": 3989.5,
      "high": 3995.89990234375,
      "low": 3983.800048828125,
      "close": 3995.89990234375
    },
    {
      "open": 3996.0,
      "high": 4000.10009765625,
      "low": 3982.699951171875,
      "close": 3986.5
    },
    {
      "open": 3987.0,
      "high": 3991.10009765625,
      "low": 3974.10009765625,
      "close": 3982.199951171875
    },
    {
      "open": 3982.5,
      "high": 4012.199951171875,
      "low": 3982.199951171875,
      "close": 3995.699951171875
    },
    {
      "open": 3995.0,
      "high": 3995.10009765625,
      "low": 3983.10009765625,
      "close": 3985.0
    },
    {
      "open": 3984.800048828125,
      "high": 3995.300048828125,
      "low": 3978.39990234375,
      "close": 3988.60009765625
    },
    {
      "open": 3988.60009765625,
      "high": 4010.699951171875,
      "low": 3988.5,
      "close": 4003.10009765625
    },
    {
      "open": 4003.10009765625,
      "high": 4006.60009765625,
      "low": 3996.699951171875,
      "close": 3997.0
    },
    {
      "open": 3996.60009765625,
      "high": 4003.800048828125,
      "low": 3991.300048828125,
      "close": 3998.39990234375
    },
    {
      "open": 3997.89990234375,
      "high": 4006.5,
      "low": 3996.800048828125,
      "close": 4001.800048828125
    },
    {
      "open": 4001.699951171875,
      "high": 4002.89990234375,
      "low": 3994.10009765625,
      "close": 3994.39990234375
    },
    {
      "open": 3994.5,
      "high": 4002.699951171875,
      "low": 3993.60009765625,
      "close": 3997.89990234375
    },
    {
      "open": 3998.199951171875,
      "high": 3999.60009765625,
      "low": 3967.699951171875,
      "close": 3969.5
    },
    {
      "open": 3970.10009765625,
      "high": 4007.89990234375,
      "low": 3963.0,
      "close": 4001.39990234375
    },
    {
      "open": 4000.699951171875,
      "high": 4008.89990234375,
      "low": 3994.199951171875,
      "close": 4005.5
    },
    {
      "open": 4005.5,
      "high": 4026.10009765625,
      "low": 4002.0,
      "close": 4024.10009765625
    },
    {
      "open": 4024.39990234375,
      "high": 4028.89990234375,
      "low": 4016.0,
      "close": 4019.60009765625
    },
    {
      "open": 4020.0,
      "high": 4024.0,
      "low": 4012.89990234375,
      "close": 4014.800048828125
    },
    {
      "open": 4014.89990234375,
      "high": 4021.300048828125,
      "low": 4011.60009765625,
      "close": 4016.10009765625
    },
    {
      "open": 4016.39990234375,
      "high": 4020.89990234375,
      "low": 4006.800048828125,
      "close": 4019.89990234375
    },
    {
      "open": 4019.89990234375,
      "high": 4023.0,
      "low": 4013.199951171875,
      "close": 4018.800048828125
    }
  ],
  "bars4h": [
    {
      "open": 4097.89990234375,
      "high": 4102.2001953125,
      "low": 4069.39990234375,
      "close": 4080.199951171875
    },
    {
      "open": 4080.5,
      "high": 4085.5,
      "low": 4057.800048828125,
      "close": 4061.800048828125
    },
    {
      "open": 4061.89990234375,
      "high": 4089.10009765625,
      "low": 4052.0,
      "close": 4076.300048828125
    },
    {
      "open": 4076.199951171875,
      "high": 4078.39990234375,
      "low": 4049.0,
      "close": 4050.89990234375
    },
    {
      "open": 4050.5,
      "high": 4054.5,
      "low": 3992.89990234375,
      "close": 4000.60009765625
    },
    {
      "open": 4000.699951171875,
      "high": 4015.5,
      "low": 3993.60009765625,
      "close": 4007.39990234375
    },
    {
      "open": 4007.699951171875,
      "high": 4025.699951171875,
      "low": 3990.39990234375,
      "close": 4019.199951171875
    },
    {
      "open": 4019.10009765625,
      "high": 4040.39990234375,
      "low": 4017.5,
      "close": 4030.39990234375
    },
    {
      "open": 4030.60009765625,
      "high": 4036.39990234375,
      "low": 4020.10009765625,
      "close": 4028.199951171875
    },
    {
      "open": 4028.199951171875,
      "high": 4112.5,
      "low": 4022.10009765625,
      "close": 4093.0
    },
    {
      "open": 4093.0,
      "high": 4108.7001953125,
      "low": 4049.199951171875,
      "close": 4060.699951171875
    },
    {
      "open": 4060.300048828125,
      "high": 4064.10009765625,
      "low": 4052.699951171875,
      "close": 4058.800048828125
    },
    {
      "open": 4059.0,
      "high": 4068.60009765625,
      "low": 4033.89990234375,
      "close": 4037.89990234375
    },
    {
      "open": 4036.89990234375,
      "high": 4044.699951171875,
      "low": 4025.60009765625,
      "close": 4030.699951171875
    },
    {
      "open": 4030.699951171875,
      "high": 4046.5,
      "low": 4023.300048828125,
      "close": 4044.5
    },
    {
      "open": 4044.89990234375,
      "high": 4080.699951171875,
      "low": 4041.800048828125,
      "close": 4053.199951171875
    },
    {
      "open": 4053.39990234375,
      "high": 4089.10009765625,
      "low": 4033.0,
      "close": 4064.0
    },
    {
      "open": 4063.699951171875,
      "high": 4071.89990234375,
      "low": 4049.199951171875,
      "close": 4050.39990234375
    },
    {
      "open": 4050.300048828125,
      "high": 4056.60009765625,
      "low": 4029.39990234375,
      "close": 4038.300048828125
    },
    {
      "open": 4038.199951171875,
      "high": 4051.800048828125,
      "low": 4027.699951171875,
      "close": 4040.300048828125
    },
    {
      "open": 4040.60009765625,
      "high": 4048.699951171875,
      "low": 3994.199951171875,
      "close": 3996.39990234375
    },
    {
      "open": 3996.300048828125,
      "high": 4021.800048828125,
      "low": 3977.10009765625,
      "close": 3996.39990234375
    },
    {
      "open": 3996.699951171875,
      "high": 3997.300048828125,
      "low": 3973.39990234375,
      "close": 3979.89990234375
    },
    {
      "open": 3980.10009765625,
      "high": 4000.10009765625,
      "low": 3976.800048828125,
      "close": 3986.5
    },
    {
      "open": 3987.0,
      "high": 4012.199951171875,
      "low": 3974.10009765625,
      "close": 3988.60009765625
    },
    {
      "open": 3988.60009765625,
      "high": 4010.699951171875,
      "low": 3988.5,
      "close": 4001.800048828125
    },
    {
      "open": 4001.699951171875,
      "high": 4007.89990234375,
      "low": 3963.0,
      "close": 4001.39990234375
    },
    {
      "open": 4000.699951171875,
      "high": 4028.89990234375,
      "low": 3994.199951171875,
      "close": 4014.800048828125
    },
    {
      "open": 4014.89990234375,
      "high": 4023.0,
      "low": 4006.800048828125,
      "close": 4018.800048828125
    }
  ],
  "calendar": null,
  "calendarError": "HTTPError: 403 Client Error: Forbidden for url: https://finnhub.io/api/v1/calendar/economic?token=d9e6h7pr01qh241amrugd9e6h7pr01qh241amrv0",
  "cot": {
    "netLong": 186682,
    "change": -7564,
    "reportDate": "2026-07-14"
  },
  "cotError": null
}