{
  "fetchedAt": "2026-07-22T19:44:10.165570+00:00",
  "gold": {
    "price": 4136.399902,
    "updatedAt": "2026-07-22T19:43:37Z"
  },
  "silver": {
    "price": 59.957001,
    "updatedAt": "2026-07-22T19:43:36Z"
  },
  "dxy": {
    "value": 101.13,
    "changePct": -0.05
  },
  "vix": {
    "value": 16.87,
    "changePct": -1.06
  },
  "wti": {
    "value": 86.85,
    "changePct": 2.28
  },
  "btc": {
    "value": 65840.47,
    "changePct": -1.0
  },
  "spx": {
    "value": 7503.26,
    "changePct": -0.08
  },
  "fred": {
    "10y_treasury": {
      "date": "2026-07-20",
      "value": 4.6
    },
    "10y_real_rate": {
      "date": "2026-07-20",
      "value": 2.35
    }
  },
  "goldapi": null,
  "correlations": {
    "dataPoints": 4,
    "minRequired": 10,
    "dxy": null,
    "realRate": null,
    "vix": null,
    "btc": null,
    "spx": null
  },
  "news": [
    {
      "time": "19:43",
      "text": "美国总统特朗普：委内瑞拉与我们合作生产石油。"
    },
    {
      "time": "19:42",
      "text": "【美威胁袭伊基础设施，伊朗军方：将不允许本地区出口一滴石油】伊朗武装部队哈塔姆安比亚中央总部当地时间22日发布声明称，美方再次威胁要打击伊朗的国家基础设施。继昨晚发出警告后，现再次宣布，霍尔木兹海峡仍处于关闭状态。若有船只确需通过该海峡，必"
    },
    {
      "time": "19:41",
      "text": "周三（7月22日）美股尾盘，美股降息赢家指数大致持平，报95.17点，早盘冲高回落、随后出现一波V形反转行情。\n“特朗普关税输家”指数跌0.13%，“特朗普金融指数”跌0.17%。"
    },
    {
      "time": "19:35",
      "text": "周三（7月22日）纽约尾盘，彭博电动汽车价格回报指数跌0.74%，报3320.72点。亚太时段高开低走，北京时间13:16以来持稳于3320点附近。"
    },
    {
      "time": "19:34",
      "text": "周三（7月22日）纽约尾盘，美元兑日元跌0.02%，报163.14日元，日内交投区间为163.22-162.69日元，北京时间15:30短线跳水——瞬间从163.13日元跌至日低。\n欧元兑日元涨0.08%，英镑兑日元跌0.05%。"
    },
    {
      "time": "19:30",
      "text": "周三（7月22日）纽约尾盘，ICE美元指数跌0.04%，报101.130点，日内交投区间为101.198-101.020点。\n彭博美元指数跌0.01%，报1219.62点，日内交投区间为1220.20-1218.35点。"
    },
    {
      "time": "19:29",
      "text": "今年入夏以来，匈牙利全境遭遇持续高温干旱天气，其境内多瑙河水位大幅下降，导致航道水深不足，河道急剧变窄，对内河货运、河轮观光旅游业带来巨大冲击，相关行业运营正面临严重挑战。\n相关统计显示，多瑙河匈牙利段今年上半年径流量，较过去三十年平均值减"
    },
    {
      "time": "19:27",
      "text": "周三（7月22日）纽约尾盘，美国10年期国债收益率涨3.45个基点，刷新日高至4.6626%。\n两年期美债收益率涨4.27个基点，报4.3042%，北京时间22:28曾刷新日高至4.3084%；30年期美债收益率涨2.20个基点，刷新日高至"
    },
    {
      "time": "19:24",
      "text": "英国外交、联邦及发展事务部（FCDO）宣布，由于伊朗安全局势变化，英国驻伊外交人员已暂时撤离。FCDO表示，英国驻伊朗大使馆将继续以远程方式运作，维持相关外交工作。（CNN）"
    },
    {
      "time": "19:22",
      "text": "相比交易员，经济学家对下周会议结果更有把握。\n76位受访经济学家全部预计，美联储将于7月28-29日会议上维持利率在3.5%-3.75%区间不变。（彭博）"
    },
    {
      "time": "19:21",
      "text": "凯文·沃什执掌下的美联储已开始在金融市场留下鲜明印记。在距离下次利率会议仅剩几天之际，交易员对于央行是否会加息仍存在明显分歧。利率互换市场显示，交易员认为美联储下周加息25个基点的概率约为30%，按兵不动概率为70%左右。在距离会议如此之近"
    },
    {
      "time": "19:17",
      "text": "周三（7月22日）纽约尾盘，彭博谷物分类指数涨2.50%，报32.9953点，北京时间14:37微幅下挫至32.1687点刷新日低随后持续上扬、23:48达到33.0597点，逼近5月19日顶部33.3410点、5月13日顶部33.6912"
    },
    {
      "time": "19:07",
      "text": "当地时间22日，美军中央司令部表示，在美军执行针对伊朗的海上封锁期间，美军导弹驱逐舰在阿拉伯海航行并监控相关行动。截至22日，美军已迫使9艘商船改道，并使1艘商船失去行动能力。（央视）"
    },
    {
      "time": "19:01",
      "text": "在岸人民币兑美元（CNY）北京时间03:00收报6.7750元，较周二夜盘收盘跌85点。成交量360.14亿美元。"
    },
    {
      "time": "19:00",
      "text": "恒生指数主连夜盘收涨0.33%，报24997点。\n恒生科技指数主连夜盘收平，报4678点。"
    },
    {
      "time": "07-16 23:00",
      "text": "[Fed] Jefferson, Navigating Economic Shocks: A Monetary Policymaker’s Perspective"
    },
    {
      "time": "07-15 17:00",
      "text": "[Fed] Cook, Economic Outlook"
    },
    {
      "time": "07-14 18:55",
      "text": "[Fed] Bowman, Responsible Innovation and Financial Inclusion"
    },
    {
      "time": "07-14 18:00",
      "text": "[Fed] Minutes of the Board's discount rate meetings on June 8 and June 17, 2026"
    },
    {
      "time": "07-14 16:40",
      "text": "[Fed] Barr, Will Artificial Intelligence Broadly Raise Living Standards or Drive Income and Wealth Inequality?"
    },
    {
      "time": "07-14 12:30",
      "text": "[Fed] Warsh, Semiannual Monetary Policy Report to the Congress"
    }
  ],
  "newsDebug": {
    "fedError": null,
    "wscnError": null,
    "avError": "节流跳过(Alpha Vantage每4小时才调用一次,避免超出免费额度)"
  },
  "priceAction": {
    "alwaysIn": "long",
    "bullTrendBarsInLast3": 0,
    "bearTrendBarsInLast3": 0,
    "isTrendStructure": true,
    "signalBarBull": false,
    "signalBarPrice": 4152.8,
    "measuredMoveLow": 4184.75,
    "measuredMoveHigh": 4229.9,
    "sma20": 4133.36,
    "currentPrice": 4139.6
  },
  "bars1h": [
    {
      "open": 4042.300048828125,
      "high": 4057.199951171875,
      "low": 4041.300048828125,
      "close": 4050.89990234375
    },
    {
      "open": 4051.699951171875,
      "high": 4056.60009765625,
      "low": 4048.39990234375,
      "close": 4054.300048828125
    },
    {
      "open": 4054.10009765625,
      "high": 4072.800048828125,
      "low": 4051.10009765625,
      "close": 4066.0
    },
    {
      "open": 4066.0,
      "high": 4088.39990234375,
      "low": 4066.0,
      "close": 4083.0
    },
    {
      "open": 4083.300048828125,
      "high": 4084.800048828125,
      "low": 4072.10009765625,
      "close": 4075.699951171875
    },
    {
      "open": 4075.60009765625,
      "high": 4076.89990234375,
      "low": 4063.60009765625,
      "close": 4067.39990234375
    },
    {
      "open": 4067.699951171875,
      "high": 4074.39990234375,
      "low": 4065.39990234375,
      "close": 4070.199951171875
    },
    {
      "open": 4070.5,
      "high": 4074.800048828125,
      "low": 4065.10009765625,
      "close": 4067.300048828125
    },
    {
      "open": 4067.699951171875,
      "high": 4068.300048828125,
      "low": 4058.89990234375,
      "close": 4060.60009765625
    },
    {
      "open": 4060.5,
      "high": 4070.39990234375,
      "low": 4055.0,
      "close": 4058.0
    },
    {
      "open": 4058.300048828125,
      "high": 4066.10009765625,
      "low": 4048.39990234375,
      "close": 4057.199951171875
    },
    {
      "open": 4057.5,
      "high": 4079.10009765625,
      "low": 4055.39990234375,
      "close": 4072.89990234375
    },
    {
      "open": 4072.5,
      "high": 4088.0,
      "low": 4069.800048828125,
      "close": 4078.60009765625
    },
    {
      "open": 4078.5,
      "high": 4083.5,
      "low": 4074.10009765625,
      "close": 4075.89990234375
    },
    {
      "open": 4076.0,
      "high": 4077.199951171875,
      "low": 4071.0,
      "close": 4073.0
    },
    {
      "open": 4072.89990234375,
      "high": 4092.5,
      "low": 4071.89990234375,
      "close": 4087.0
    },
    {
      "open": 4087.0,
      "high": 4090.300048828125,
      "low": 4084.699951171875,
      "close": 4088.60009765625
    },
    {
      "open": 4088.60009765625,
      "high": 4090.89990234375,
      "low": 4080.89990234375,
      "close": 4082.199951171875
    },
    {
      "open": 4084.699951171875,
      "high": 4089.0,
      "low": 4081.0,
      "close": 4084.60009765625
    },
    {
      "open": 4084.39990234375,
      "high": 4087.39990234375,
      "low": 4083.300048828125,
      "close": 4085.199951171875
    },
    {
      "open": 4085.5,
      "high": 4107.5,
      "low": 4081.10009765625,
      "close": 4101.60009765625
    },
    {
      "open": 4102.2998046875,
      "high": 4128.39990234375,
      "low": 4100.7998046875,
      "close": 4126.0
    },
    {
      "open": 4126.39990234375,
      "high": 4135.2998046875,
      "low": 4123.10009765625,
      "close": 4134.7001953125
    },
    {
      "open": 4134.7998046875,
      "high": 4146.0,
      "low": 4133.60009765625,
      "close": 4135.5
    },
    {
      "open": 4135.10009765625,
      "high": 4135.60009765625,
      "low": 4129.39990234375,
      "close": 4131.7998046875
    },
    {
      "open": 4131.60009765625,
      "high": 4138.60009765625,
      "low": 4127.5,
      "close": 4135.5
    },
    {
      "open": 4135.39990234375,
      "high": 4140.0,
      "low": 4117.7998046875,
      "close": 4121.0
    },
    {
      "open": 4120.7998046875,
      "high": 4127.39990234375,
      "low": 4113.2998046875,
      "close": 4114.60009765625
    },
    {
      "open": 4115.0,
      "high": 4124.39990234375,
      "low": 4114.7998046875,
      "close": 4122.2998046875
    },
    {
      "open": 4122.60009765625,
      "high": 4126.60009765625,
      "low": 4117.5,
      "close": 4118.7998046875
    },
    {
      "open": 4119.2001953125,
      "high": 4126.10009765625,
      "low": 4119.2001953125,
      "close": 4121.2001953125
    },
    {
      "open": 4121.7998046875,
      "high": 4127.89990234375,
      "low": 4117.2001953125,
      "close": 4127.39990234375
    },
    {
      "open": 4127.5,
      "high": 4139.5,
      "low": 4110.39990234375,
      "close": 4117.0
    },
    {
      "open": 4117.10009765625,
      "high": 4161.5,
      "low": 4117.0,
      "close": 4160.0
    },
    {
      "open": 4159.7998046875,
      "high": 4168.7998046875,
      "low": 4148.60009765625,
      "close": 4153.39990234375
    },
    {
      "open": 4153.5,
      "high": 4171.39990234375,
      "low": 4153.39990234375,
      "close": 4164.10009765625
    },
    {
      "open": 4164.39990234375,
      "high": 4164.5,
      "low": 4150.10009765625,
      "close": 4152.7998046875
    },
    {
      "open": 4152.7998046875,
      "high": 4153.60009765625,
      "low": 4143.7998046875,
      "close": 4148.10009765625
    },
    {
      "open": 4147.89990234375,
      "high": 4148.39990234375,
      "low": 4137.5,
      "close": 4141.7998046875
    },
    {
      "open": 4141.39990234375,
      "high": 4142.5,
      "low": 4137.10009765625,
      "close": 4139.60009765625
    }
  ],
  "bars4h": [
    {
      "open": 4053.39990234375,
      "high": 4089.10009765625,
      "low": 4033.0,
      "close": 4064.0
    },
    {
      "open": 4063.699951171875,
      "high": 4071.89990234375,
      "low": 4049.199951171875,
      "close": 4050.39990234375
    },
    {
      "open": 4050.300048828125,
      "high": 4056.60009765625,
      "low": 4029.39990234375,
      "close": 4038.300048828125
    },
    {
      "open": 4038.199951171875,
      "high": 4051.800048828125,
      "low": 4027.699951171875,
      "close": 4040.300048828125
    },
    {
      "open": 4040.60009765625,
      "high": 4048.699951171875,
      "low": 3994.199951171875,
      "close": 3996.39990234375
    },
    {
      "open": 3996.300048828125,
      "high": 4021.800048828125,
      "low": 3977.10009765625,
      "close": 3996.39990234375
    },
    {
      "open": 3996.699951171875,
      "high": 3997.300048828125,
      "low": 3973.39990234375,
      "close": 3979.89990234375
    },
    {
      "open": 3980.10009765625,
      "high": 4000.10009765625,
      "low": 3976.800048828125,
      "close": 3986.5
    },
    {
      "open": 3987.0,
      "high": 4012.199951171875,
      "low": 3974.10009765625,
      "close": 3988.60009765625
    },
    {
      "open": 3988.60009765625,
      "high": 4010.699951171875,
      "low": 3988.5,
      "close": 4001.800048828125
    },
    {
      "open": 4001.699951171875,
      "high": 4007.89990234375,
      "low": 3963.0,
      "close": 4001.39990234375
    },
    {
      "open": 4000.699951171875,
      "high": 4028.89990234375,
      "low": 3994.199951171875,
      "close": 4014.800048828125
    },
    {
      "open": 4014.89990234375,
      "high": 4023.0,
      "low": 3996.89990234375,
      "close": 3997.89990234375
    },
    {
      "open": 3999.300048828125,
      "high": 4034.199951171875,
      "low": 3986.5,
      "close": 4027.10009765625
    },
    {
      "open": 4026.699951171875,
      "high": 4032.699951171875,
      "low": 4007.0,
      "close": 4008.199951171875
    },
    {
      "open": 4008.0,
      "high": 4035.5,
      "low": 4006.5,
      "close": 4029.0
    },
    {
      "open": 4029.0,
      "high": 4046.0,
      "low": 4001.60009765625,
      "close": 4010.5
    },
    {
      "open": 4010.39990234375,
      "high": 4023.89990234375,
      "low": 4005.199951171875,
      "close": 4012.10009765625
    },
    {
      "open": 4011.5,
      "high": 4022.199951171875,
      "low": 4003.300048828125,
      "close": 4014.39990234375
    },
    {
      "open": 4014.5,
      "high": 4057.199951171875,
      "low": 4008.300048828125,
      "close": 4050.89990234375
    },
    {
      "open": 4051.699951171875,
      "high": 4088.39990234375,
      "low": 4048.39990234375,
      "close": 4075.699951171875
    },
    {
      "open": 4075.60009765625,
      "high": 4076.89990234375,
      "low": 4058.89990234375,
      "close": 4060.60009765625
    },
    {
      "open": 4060.5,
      "high": 4088.0,
      "low": 4048.39990234375,
      "close": 4078.60009765625
    },
    {
      "open": 4078.5,
      "high": 4092.5,
      "low": 4071.0,
      "close": 4088.60009765625
    },
    {
      "open": 4088.60009765625,
      "high": 4107.5,
      "low": 4080.89990234375,
      "close": 4101.60009765625
    },
    {
      "open": 4102.2998046875,
      "high": 4146.0,
      "low": 4100.7998046875,
      "close": 4131.7998046875
    },
    {
      "open": 4131.60009765625,
      "high": 4140.0,
      "low": 4113.2998046875,
      "close": 4122.2998046875
    },
    {
      "open": 4122.60009765625,
      "high": 4139.5,
      "low": 4110.39990234375,
      "close": 4117.0
    },
    {
      "open": 4117.10009765625,
      "high": 4171.39990234375,
      "low": 4117.0,
      "close": 4152.7998046875
    },
    {
      "open": 4152.7998046875,
      "high": 4153.60009765625,
      "low": 4137.10009765625,
      "close": 4139.60009765625
    }
  ],
  "calendar": null,
  "calendarError": "HTTPError: 403 Client Error: Forbidden for url: https://finnhub.io/api/v1/calendar/economic?token=d9e6h7pr01qh241amrugd9e6h7pr01qh241amrv0 | FMP备选也失败: 未设置 FMP_KEY 环境变量（可选数据源，不影响其他部分）",
  "cot": {
    "netLong": 186682,
    "change": -7564,
    "reportDate": "2026-07-14"
  },
  "cotError": null,
  "gld": null,
  "gldError": "Error: new-line character seen in unquoted field - do you need to open the file with newline=''?"
}