{
  "fetchedAt": "2026-07-20T04:56:06.488392+00:00",
  "gold": {
    "price": 4022.300049,
    "updatedAt": "2026-07-20T04:55:24Z"
  },
  "silver": {
    "price": 57.068001,
    "updatedAt": "2026-07-20T04:55:24Z"
  },
  "dxy": null,
  "vix": {
    "value": 18.77,
    "changePct": 12.19
  },
  "wti": null,
  "btc": null,
  "spx": {
    "value": 7457.69,
    "changePct": -1.01
  },
  "fred": {
    "10y_treasury": {
      "date": "2026-07-16",
      "value": 4.57
    },
    "10y_real_rate": {
      "date": "2026-07-16",
      "value": 2.35
    }
  },
  "goldapi": null,
  "correlations": {
    "dataPoints": 2,
    "minRequired": 10,
    "dxy": null,
    "realRate": null,
    "vix": null,
    "btc": null,
    "spx": null
  },
  "news": [
    {
      "time": "04:44",
      "text": "有投资者向森麒麟提问，公司西班牙工厂项目取消了吗？要是没取消有什么进展吗？ 7月20日，公司回答表示，公司西班牙项目暂未有实质性推进。后续若有相关进展将及时履行信息披露义务。"
    },
    {
      "time": "04:37",
      "text": "科威特方面表示，目前正在应对敌对无人机的威胁。"
    },
    {
      "time": "04:36",
      "text": "巴基斯坦KSE-100指数跌1.3%。"
    },
    {
      "time": "04:31",
      "text": "恒力石化公告，公司拟以自有资金或自筹资金2亿元（含）-3亿元（含）回购公司股份。回购股份价格不超过人民币25元/股（含），该价格不高于董事会通过回购股份决议前30个交易日公司股票交易均价的150%。"
    },
    {
      "time": "04:30",
      "text": "沪指、创业板指均涨超1%，油气、煤炭板块集体走强。\n恒指半日涨2.1%，恒生科技指数涨2.9%。阿里巴巴涨超5%，智谱逆市跌13%。\n日本股市今日休市，韩国首尔综指再次下跌，盘中一度跌超5%。\n连续第14个月维持不变！7月LPR报价出炉：5"
    },
    {
      "time": "04:30",
      "text": "① 14:00 德国6月PPI；\n② 20:30 加拿大6月CPI；\n③ 22:00 美国6月谘商会领先指标；\n微信小程序搜索“见闻历”，了解更多。"
    },
    {
      "time": "04:27",
      "text": "中国信息通信研究院依托人工智能软硬件协同创新与适配验证中心（位于北京经开区国家信创园），基于AISHPerf人工智能软硬件基准体系，正式启动“AISHPerf大模型训推工程实践性能基准研究工作”。该项工作以“建基准、聚数据、促优化”为核心方"
    },
    {
      "time": "04:23",
      "text": "三峡能源：控股股东三峡集团计划在未来12个月内通过二级市场增持公司股份，包括集中竞价、大宗交易等交易方式，增持金额不低于人民币15亿元、不高于人民币30亿元。"
    },
    {
      "time": "04:19",
      "text": "阡视科技在2026世界人工智能大会（WAIC 2026）上发布适配Token工厂的wylon超节点系统。据介绍，本次推出wylon Q72/288超节点机型，单机柜搭载72颗国产GPU，四机柜组网可扩容至288卡，配备超大显存、高互联带宽与"
    },
    {
      "time": "04:17",
      "text": "韩国首尔综指日内跌超5%，此前一度接近转涨。"
    },
    {
      "time": "04:14",
      "text": "据上汽集团消息，在2026世界人工智能大会（WAIC）“数智驱动 模速智行”高级别自动驾驶创新发展论坛上，享道出行正式宣布启动上汽Robotaxi量产定制车项目，新车计划于2027年亮相。"
    },
    {
      "time": "04:13",
      "text": "中国太保公告称，公司坚信中国经济长期向好的基本面，坚定看好中国资本市场发展前景，坚持“价值投资、长期投资、稳健投资、责任投资”的投资理念，看好中国权益市场长期配置价值。今年以来，公司持续发挥保险资金长期投资优势，加大权益配置比例。后续将继续"
    },
    {
      "time": "04:12",
      "text": "红塔证券：董事长提议回购公司部分股份，回购资金总额不低于人民币5000万元（含），不超过人民币1亿元（含），回购股份用于减少注册资本。"
    },
    {
      "time": "04:11",
      "text": "中国软件国际：与月之暗面签署Token分成及联合创新合作协议。"
    },
    {
      "time": "04:11",
      "text": "上汽集团：收到控股股东承诺函，上汽总公司承诺自承诺函签署之日（2026年7月20日）起6个月内，不以任何方式减持其持有的公司股份，包括因公司资本公积转增股本、派送股票红利等事项取得的新增股份。"
    },
    {
      "time": "07-19 18:43",
      "text": "[AV] ING Groep stock holds firm as capital return and net interest income support valuation"
    },
    {
      "time": "07-19 14:40",
      "text": "[AV] Are XRP ETFs Still Bringing In Money?"
    },
    {
      "time": "07-19 13:41",
      "text": "[AV] VanEck's GDX ETF marks 20 years as a key gold investment amid rising global economic risks."
    },
    {
      "time": "07-19 13:18",
      "text": "[AV] Apple raises iPhone prices in Japan by as much as 11% amid weak yen (AAPL:NASDAQ)"
    },
    {
      "time": "07-19 12:43",
      "text": "[AV] The Week Ahead: Infosys Q1 Results, US-Iran War, India PMI Data, EU Interest Rate Decision, UK CPI Data"
    },
    {
      "time": "07-19 11:52",
      "text": "[AV] Equity Residential stock trades steadily as funds from operations support valuation"
    },
    {
      "time": "07-19 09:43",
      "text": "[AV] Bitcoin Price Is Up On BlackRock's IBIT ETF Inflows"
    },
    {
      "time": "07-19 09:40",
      "text": "[AV] NVR stock trades steady as homebuilder margins stay elevated"
    },
    {
      "time": "07-19 09:30",
      "text": "[AV] Big Food Is Running Out of Moves with Shoppers and Investors"
    },
    {
      "time": "07-19 07:10",
      "text": "[AV] HYZD ETF Profile: Dividends, Returns (BOATS:HYZD)"
    },
    {
      "time": "07-16 23:00",
      "text": "[Fed] Jefferson, Navigating Economic Shocks: A Monetary Policymaker’s Perspective"
    },
    {
      "time": "07-15 17:00",
      "text": "[Fed] Cook, Economic Outlook"
    },
    {
      "time": "07-14 18:55",
      "text": "[Fed] Bowman, Responsible Innovation and Financial Inclusion"
    },
    {
      "time": "07-14 18:00",
      "text": "[Fed] Minutes of the Board's discount rate meetings on June 8 and June 17, 2026"
    },
    {
      "time": "07-14 16:40",
      "text": "[Fed] Barr, Will Artificial Intelligence Broadly Raise Living Standards or Drive Income and Wealth Inequality?"
    },
    {
      "time": "07-14 12:30",
      "text": "[Fed] Warsh, Semiannual Monetary Policy Report to the Congress"
    }
  ],
  "newsDebug": null,
  "priceAction": {
    "alwaysIn": "long",
    "bullTrendBarsInLast3": 0,
    "bearTrendBarsInLast3": 0,
    "isTrendStructure": false,
    "signalBarBull": false,
    "signalBarPrice": 4023.9,
    "measuredMoveLow": 4058.05,
    "measuredMoveHigh": 4092.2,
    "sma20": 4006.07,
    "currentPrice": 4023.9
  },
  "bars1h": [
    {
      "open": 4040.60009765625,
      "high": 4043.199951171875,
      "low": 4035.699951171875,
      "close": 4037.39990234375
    },
    {
      "open": 4037.199951171875,
      "high": 4040.10009765625,
      "low": 4034.39990234375,
      "close": 4035.10009765625
    },
    {
      "open": 4035.199951171875,
      "high": 4048.39990234375,
      "low": 4026.199951171875,
      "close": 4044.10009765625
    },
    {
      "open": 4044.39990234375,
      "high": 4048.699951171875,
      "low": 3994.199951171875,
      "close": 3996.39990234375
    },
    {
      "open": 3996.300048828125,
      "high": 4012.60009765625,
      "low": 3977.10009765625,
      "close": 3994.0
    },
    {
      "open": 3993.89990234375,
      "high": 4011.0,
      "low": 3991.199951171875,
      "close": 4002.0
    },
    {
      "open": 4002.199951171875,
      "high": 4021.800048828125,
      "low": 3993.300048828125,
      "close": 4011.800048828125
    },
    {
      "open": 4011.39990234375,
      "high": 4012.300048828125,
      "low": 3986.5,
      "close": 3996.39990234375
    },
    {
      "open": 3996.699951171875,
      "high": 3997.300048828125,
      "low": 3983.89990234375,
      "close": 3989.5
    },
    {
      "open": 3989.699951171875,
      "high": 3995.199951171875,
      "low": 3981.0,
      "close": 3984.699951171875
    },
    {
      "open": 3984.89990234375,
      "high": 3990.800048828125,
      "low": 3973.39990234375,
      "close": 3984.60009765625
    },
    {
      "open": 3984.800048828125,
      "high": 3984.800048828125,
      "low": 3976.199951171875,
      "close": 3979.89990234375
    },
    {
      "open": 3980.10009765625,
      "high": 3984.10009765625,
      "low": 3976.800048828125,
      "close": 3982.10009765625
    },
    {
      "open": 3982.10009765625,
      "high": 3989.89990234375,
      "low": 3978.60009765625,
      "close": 3989.199951171875
    },
    {
      "open": 3989.5,
      "high": 3995.89990234375,
      "low": 3983.800048828125,
      "close": 3995.89990234375
    },
    {
      "open": 3996.0,
      "high": 4000.10009765625,
      "low": 3982.699951171875,
      "close": 3986.5
    },
    {
      "open": 3987.0,
      "high": 3991.10009765625,
      "low": 3974.10009765625,
      "close": 3982.199951171875
    },
    {
      "open": 3982.5,
      "high": 4012.199951171875,
      "low": 3982.199951171875,
      "close": 3995.699951171875
    },
    {
      "open": 3995.0,
      "high": 3995.10009765625,
      "low": 3983.10009765625,
      "close": 3985.0
    },
    {
      "open": 3984.800048828125,
      "high": 3995.300048828125,
      "low": 3978.39990234375,
      "close": 3988.60009765625
    },
    {
      "open": 3988.60009765625,
      "high": 4010.699951171875,
      "low": 3988.5,
      "close": 4003.10009765625
    },
    {
      "open": 4003.10009765625,
      "high": 4006.60009765625,
      "low": 3996.699951171875,
      "close": 3997.0
    },
    {
      "open": 3996.60009765625,
      "high": 4003.800048828125,
      "low": 3991.300048828125,
      "close": 3998.39990234375
    },
    {
      "open": 3997.89990234375,
      "high": 4006.5,
      "low": 3996.800048828125,
      "close": 4001.800048828125
    },
    {
      "open": 4001.699951171875,
      "high": 4002.89990234375,
      "low": 3994.10009765625,
      "close": 3994.39990234375
    },
    {
      "open": 3994.5,
      "high": 4002.699951171875,
      "low": 3993.60009765625,
      "close": 3997.89990234375
    },
    {
      "open": 3998.199951171875,
      "high": 3999.60009765625,
      "low": 3967.699951171875,
      "close": 3969.5
    },
    {
      "open": 3970.10009765625,
      "high": 4007.89990234375,
      "low": 3963.0,
      "close": 4001.39990234375
    },
    {
      "open": 4000.699951171875,
      "high": 4008.89990234375,
      "low": 3994.199951171875,
      "close": 4005.5
    },
    {
      "open": 4005.5,
      "high": 4026.10009765625,
      "low": 4002.0,
      "close": 4024.10009765625
    },
    {
      "open": 4024.39990234375,
      "high": 4028.89990234375,
      "low": 4016.0,
      "close": 4019.60009765625
    },
    {
      "open": 4020.0,
      "high": 4024.0,
      "low": 4012.89990234375,
      "close": 4014.800048828125
    },
    {
      "open": 4014.89990234375,
      "high": 4021.300048828125,
      "low": 4011.60009765625,
      "close": 4016.10009765625
    },
    {
      "open": 4016.39990234375,
      "high": 4020.89990234375,
      "low": 4006.800048828125,
      "close": 4019.89990234375
    },
    {
      "open": 4019.89990234375,
      "high": 4023.0,
      "low": 4013.199951171875,
      "close": 4018.800048828125
    },
    {
      "open": 4001.0,
      "high": 4004.39990234375,
      "low": 3996.89990234375,
      "close": 3997.89990234375
    },
    {
      "open": 3999.300048828125,
      "high": 4000.10009765625,
      "low": 3993.0,
      "close": 3999.199951171875
    },
    {
      "open": 3999.60009765625,
      "high": 4014.5,
      "low": 3986.5,
      "close": 4013.699951171875
    },
    {
      "open": 4013.5,
      "high": 4025.699951171875,
      "low": 4000.10009765625,
      "close": 4004.5
    },
    {
      "open": 4028.699951171875,
      "high": 4031.300048828125,
      "low": 4023.89990234375,
      "close": 4023.89990234375
    }
  ],
  "bars4h": [
    {
      "open": 4068.10009765625,
      "high": 4080.89990234375,
      "low": 4052.0,
      "close": 4072.800048828125
    },
    {
      "open": 4072.800048828125,
      "high": 4089.10009765625,
      "low": 4055.0,
      "close": 4064.0
    },
    {
      "open": 4064.0,
      "high": 4075.5,
      "low": 4005.800048828125,
      "close": 4023.300048828125
    },
    {
      "open": 4023.10009765625,
      "high": 4025.5,
      "low": 3992.89990234375,
      "close": 4009.300048828125
    },
    {
      "open": 4009.39990234375,
      "high": 4015.5,
      "low": 3990.39990234375,
      "close": 4011.60009765625
    },
    {
      "open": 4010.800048828125,
      "high": 4029.699951171875,
      "low": 3998.60009765625,
      "close": 4026.699951171875
    },
    {
      "open": 4027.199951171875,
      "high": 4040.39990234375,
      "low": 4020.800048828125,
      "close": 4022.60009765625
    },
    {
      "open": 4022.39990234375,
      "high": 4112.5,
      "low": 4020.10009765625,
      "close": 4083.89990234375
    },
    {
      "open": 4084.0,
      "high": 4108.7001953125,
      "low": 4063.39990234375,
      "close": 4068.300048828125
    },
    {
      "open": 4068.800048828125,
      "high": 4072.199951171875,
      "low": 4049.199951171875,
      "close": 4058.300048828125
    },
    {
      "open": 4059.800048828125,
      "high": 4068.60009765625,
      "low": 4041.199951171875,
      "close": 4042.89990234375
    },
    {
      "open": 4043.0,
      "high": 4048.39990234375,
      "low": 4028.0,
      "close": 4041.0
    },
    {
      "open": 4040.89990234375,
      "high": 4041.699951171875,
      "low": 4023.300048828125,
      "close": 4036.300048828125
    },
    {
      "open": 4036.39990234375,
      "high": 4080.699951171875,
      "low": 4032.10009765625,
      "close": 4068.5
    },
    {
      "open": 4068.699951171875,
      "high": 4073.699951171875,
      "low": 4033.0,
      "close": 4068.699951171875
    },
    {
      "open": 4069.199951171875,
      "high": 4089.10009765625,
      "low": 4055.199951171875,
      "close": 4065.60009765625
    },
    {
      "open": 4065.800048828125,
      "high": 4068.0,
      "low": 4029.39990234375,
      "close": 4036.89990234375
    },
    {
      "open": 4036.800048828125,
      "high": 4051.800048828125,
      "low": 4027.699951171875,
      "close": 4035.800048828125
    },
    {
      "open": 4035.60009765625,
      "high": 4043.199951171875,
      "low": 4027.800048828125,
      "close": 4035.10009765625
    },
    {
      "open": 4035.199951171875,
      "high": 4048.699951171875,
      "low": 3977.10009765625,
      "close": 4002.0
    },
    {
      "open": 4002.199951171875,
      "high": 4021.800048828125,
      "low": 3981.0,
      "close": 3984.699951171875
    },
    {
      "open": 3984.89990234375,
      "high": 3990.800048828125,
      "low": 3973.39990234375,
      "close": 3989.199951171875
    },
    {
      "open": 3989.5,
      "high": 4012.199951171875,
      "low": 3974.10009765625,
      "close": 3995.699951171875
    },
    {
      "open": 3995.0,
      "high": 4010.699951171875,
      "low": 3978.39990234375,
      "close": 3997.0
    },
    {
      "open": 3996.60009765625,
      "high": 4006.5,
      "low": 3991.300048828125,
      "close": 3997.89990234375
    },
    {
      "open": 3998.199951171875,
      "high": 4026.10009765625,
      "low": 3963.0,
      "close": 4024.10009765625
    },
    {
      "open": 4024.39990234375,
      "high": 4028.89990234375,
      "low": 4006.800048828125,
      "close": 4019.89990234375
    },
    {
      "open": 4019.89990234375,
      "high": 4023.0,
      "low": 3986.5,
      "close": 4013.699951171875
    },
    {
      "open": 4013.5,
      "high": 4031.300048828125,
      "low": 4000.10009765625,
      "close": 4023.89990234375
    }
  ],
  "calendar": null,
  "calendarError": "HTTPError: 403 Client Error: Forbidden for url: https://finnhub.io/api/v1/calendar/economic?token=d9e6h7pr01qh241amrugd9e6h7pr01qh241amrv0",
  "cot": {
    "netLong": 186682,
    "change": -7564,
    "reportDate": "2026-07-14"
  },
  "cotError": null
}