{
  "fetchedAt": "2026-07-09T11:24:57.617292+00:00",
  "gold": {
    "price": 4102.100098,
    "updatedAt": "2026-07-09T11:24:52Z"
  },
  "silver": {
    "price": 58.952,
    "updatedAt": "2026-07-09T11:24:51Z"
  },
  "dxy": {
    "value": 101.01,
    "changePct": -0.04
  },
  "vix": {
    "value": 17.17,
    "changePct": 1.6
  },
  "wti": {
    "value": 74.0,
    "changePct": 0.65
  },
  "fred": {
    "10y_treasury": {
      "date": "2026-07-07",
      "value": 4.55
    },
    "10y_real_rate": {
      "date": "2026-07-07",
      "value": 2.3
    }
  },
  "goldapi": null,
  "news": [
    {
      "category": "central_banks",
      "categoryLabel": "央行动向",
      "title": "Opening Remarks On Government Securities Settlement",
      "link": "https://www.investing.com/central-banks/federal-reserve/speeches/opening-remarks-on-government-securities-settlement-200162218",
      "publishedAt": "2016-10-24T13:22:00+00:00"
    },
    {
      "category": "central_banks",
      "categoryLabel": "央行动向",
      "title": "Japan's Economy and Monetary Policy",
      "link": "https://www.investing.com/central-banks/bank-of-japan/speeches/japan's-economy-and-monetary-policy-200146900",
      "publishedAt": "2016-08-04T09:00:00+00:00"
    },
    {
      "category": "central_banks",
      "categoryLabel": "央行动向",
      "title": "Assessing The Implications Of Negative Interest Rates",
      "link": "https://www.investing.com/central-banks/european-central-bank/speeches/assessing-the-implications-of-negative-interest-rates-200146901",
      "publishedAt": "2016-07-28T09:00:00+00:00"
    },
    {
      "category": "central_banks",
      "categoryLabel": "央行动向",
      "title": "Brexit And Monetary Policy",
      "link": "https://www.investing.com/central-banks/bank-of-england/speeches/brexit-and-monetary-policy-200144190",
      "publishedAt": "2016-07-18T09:00:00+00:00"
    },
    {
      "category": "commodities",
      "categoryLabel": "大宗商品",
      "title": "Bernstein sees higher gold prices in H2’26, sets new price target",
      "link": "https://www.investing.com/news/commodities-news/bernstein-sees-higher-gold-prices-in-h226-sets-new-price-target-4783519",
      "publishedAt": null
    },
    {
      "category": "commodities",
      "categoryLabel": "大宗商品",
      "title": "Morning Bid: Markets remain long TACO",
      "link": "https://www.investing.com/news/commodities-news/morning-bid-markets-remain-long-taco-4783507",
      "publishedAt": null
    },
    {
      "category": "commodities",
      "categoryLabel": "大宗商品",
      "title": "Iran says it hits US military targets in Gulf, prepares to bury slain leader",
      "link": "https://www.investing.com/news/commodities-news/iran-says-it-hits-us-military-targets-in-gulf-prepares-to-bury-slain-leader-4783457",
      "publishedAt": null
    },
    {
      "category": "commodities",
      "categoryLabel": "大宗商品",
      "title": "Iraq seeks higher output quota but will stay in OPEC",
      "link": "https://www.investing.com/news/commodities-news/iraq-seeks-higher-output-quota-but-will-stay-in-opec-93CH-4783454",
      "publishedAt": null
    },
    {
      "category": "economy",
      "categoryLabel": "经济数据",
      "title": "US relies more on foreign stock than debt flows, a dollar risk, Deutsche Bank warns",
      "link": "https://www.investing.com/news/economy-news/us-relies-more-on-foreign-stock-than-debt-flows-a-dollar-risk-deutsche-bank-warns-4783665",
      "publishedAt": null
    },
    {
      "category": "economy",
      "categoryLabel": "经济数据",
      "title": "BofA sees Bank of Korea rate hike on inflation and FX concerns",
      "link": "https://www.investing.com/news/economy-news/bofa-sees-bank-of-korea-rate-hike-on-inflation-and-fx-concerns-93CH-4783600",
      "publishedAt": null
    },
    {
      "category": "economy",
      "categoryLabel": "经济数据",
      "title": "Wall St futures rebound as oil retreats, investors weigh US-Iran tensions",
      "link": "https://www.investing.com/news/economy-news/wall-st-futures-rebound-as-oil-retreats-investors-weigh-usiran-tensions-4783449",
      "publishedAt": null
    },
    {
      "category": "economy",
      "categoryLabel": "经济数据",
      "title": "European Commission imposes anti-dumping duties on Chinese tyres",
      "link": "https://www.investing.com/news/economy-news/european-commission-imposes-antidumping-duties-on-chinese-tyres-93CH-4783491",
      "publishedAt": null
    }
  ]
}